{
  "0": {
    "question": "Are you at home or are you a guest at someone's place during the holiday?",
    "answers": [
      {
        "answer": "At home",
        "question": "Have you already prepared all your Shabbat dishes before the start of the holiday?",
        "answers": [
          {
            "answer": [
              "Yes",
              "No"
            ],
            "question": "Will you be reheating dishes for Shabbat during the holiday?",
            "answers": [
              {
                "answer": "Yes",
                "question": "Does any of the dishes you plan to reheat contain a sauce?",
                "answers": [
                  {
                    "answer": "Yes",
                    "indications": [
                      "An Eruv Tavshilin with a blessing is required, as reheating a liquid dish is considered cooking according to Halakha. This involves preparation for Shabbat."
                    ]
                  },
                  {
                    "answer": "No",
                    "indications": [
                      "Make an Eruv Tavshilin without a blessing, as the dish is dry."
                    ]
                  }
                ]
              },
              {
                "answer": "No",
                "question": "",
                "indications": [
                  "If you plan to cook a small dish on the holiday in honor of Shabbat, like hard-boiled eggs: Make an Eruv Tavshilin with a blessing.",
                  "According to some opinions, it is recommended to make an Eruv without a blessing in all cases, unless you actually prepare a dish.",
                  "Regarding lighting Shabbat candles: It is not necessary to make an Eruv Tavshilin to light the Shabbat candles."
                ]
              }
            ]
          }
        ]
      },
      {
        "answer": "Guest at someone's place",
        "question": "Are you a guest for the holiday?",
        "answers": [
          {
            "answer": "Yes, and I am staying with the host for Shabbat",
            "indications": [
              "You do not need to make an Eruv Tavshilin, as you rely on the host. You can also ask the host to include you in their Eruv or make an Eruv without a blessing."
            ]
          },
          {
            "answer": "Yes, but I am returning home after the holiday meal",
            "indications": [
              "It is preferable to cook or reheat a dish at your place for Shabbat and make an Eruv with a blessing."
            ]
          }
        ]
      },
      {
        "answer": "You are at a hotel for the holiday",
        "question": "Are you staying at a hotel during the holiday and remaining there until Shabbat?",
        "answers": [
          {
            "answer": "Yes",
            "indications": [
              "You are not required to make an Eruv Tavshilin, as you are not preparing anything for Shabbat. However, if you cook or reheat a dish in your room in honor of Shabbat, you can make an Eruv Tavshilin with a blessing."
            ]
          }
        ]
      }
    ]
  }
}